matgl/__init__.py
matgl/cli.py
matgl/config.py
matgl/py.typed
matgl/apps/__init__.py
matgl/apps/_pes_dgl.py
matgl/apps/_pes_pyg.py
matgl/apps/pes.py
matgl/data/__init__.py
matgl/data/transformer.py
matgl/electrostatics/__init__.py
matgl/electrostatics/_elec_pot_dgl.py
matgl/electrostatics/_fast_qeq_dgl.py
matgl/ext/__init__.py
matgl/ext/_ase_dgl.py
matgl/ext/_ase_pyg.py
matgl/ext/_pymatgen_dgl.py
matgl/ext/_pymatgen_pyg.py
matgl/ext/ase.py
matgl/ext/pymatgen.py
matgl/graph/__init__.py
matgl/graph/_compute_dgl.py
matgl/graph/_compute_pyg.py
matgl/graph/_converters_dgl.py
matgl/graph/_converters_pyg.py
matgl/graph/_data_dgl.py
matgl/graph/_data_pyg.py
matgl/graph/converters.py
matgl/graph/data.py
matgl/layers/__init__.py
matgl/layers/_activations.py
matgl/layers/_atom_ref_dgl.py
matgl/layers/_atom_ref_pyg.py
matgl/layers/_basis.py
matgl/layers/_bond.py
matgl/layers/_core.py
matgl/layers/_core_dgl.py
matgl/layers/_embedding_dgl.py
matgl/layers/_embedding_pyg.py
matgl/layers/_graph_convolution_dgl.py
matgl/layers/_graph_convolution_pyg.py
matgl/layers/_norm.py
matgl/layers/_readout_dgl.py
matgl/layers/_readout_pyg.py
matgl/layers/_so3.py
matgl/layers/_three_body.py
matgl/layers/_zbl_dgl.py
matgl/layers/_zbl_pyg.py
matgl/models/__init__.py
matgl/models/_chgnet.py
matgl/models/_core.py
matgl/models/_m3gnet.py
matgl/models/_megnet.py
matgl/models/_qet_dgl.py
matgl/models/_so3net.py
matgl/models/_tensornet_dgl.py
matgl/models/_tensornet_pyg.py
matgl/models/_wrappers.py
matgl/utils/__init__.py
matgl/utils/_training_dgl.py
matgl/utils/_training_pyg.py
matgl/utils/cutoff.py
matgl/utils/io.py
matgl/utils/maths.py
matgl/utils/sb_roots.npy
matgl/utils/so3.py
matgl/utils/training.py
matgl-2.0.6.dist-info/licenses/LICENSE
matgl-2.0.6.dist-info/METADATA
matgl-2.0.6.dist-info/WHEEL
matgl-2.0.6.dist-info/entry_points.txt
matgl-2.0.6.dist-info/top_level.txt
matgl-2.0.6.dist-info/RECORD
