Metadata-Version: 2.4
Name: matgl
Version: 2.0.6
Summary: MatGL is a framework for graph deep learning for materials science.
Author-email: Tsz Wai Ko <t1ko@ucsd.edu>, Marcel Nassar <marcel.nassar@intel.com>, Ji Qi <j1qi@ucsd.edu>, Santiago Miret <santiago.miret@intel.com>, Eliott Liu <elliottliu17@gmail.com>, Bowen Deng <bowendeng@berkeley.edu>, Luis Barroso-Luque <lbluque@berkeley.edu>, Shyue Ping Ong <ongsp@ucsd.edu>
License: BSD-3-Clause
Keywords: materials,interatomic potential,force field,science,property prediction,AI,machine learning,graph,deep learning
Classifier: Development Status :: 4 - Beta
Classifier: Intended Audience :: Science/Research
Classifier: License :: OSI Approved :: BSD License
Classifier: Operating System :: OS Independent
Classifier: Programming Language :: Python :: 3.10
Classifier: Programming Language :: Python :: 3.11
Classifier: Programming Language :: Python :: 3.12
Classifier: Programming Language :: Python :: 3
Classifier: Topic :: Scientific/Engineering :: Chemistry
Classifier: Topic :: Scientific/Engineering :: Information Analysis
Classifier: Topic :: Scientific/Engineering :: Physics
Classifier: Topic :: Software Development :: Libraries :: Python Modules
Requires-Python: >=3.10
License-File: LICENSE
Requires-Dist: ase
Requires-Dist: torch<=2.8.0
Requires-Dist: torchdata
Requires-Dist: pymatgen
Requires-Dist: lightning<=2.6.0
Requires-Dist: pydantic
Requires-Dist: boto3
Requires-Dist: numpy<3.0
Requires-Dist: torch-geometric
Provides-Extra: dgl
Requires-Dist: dgl<=2.1.0; sys_platform == "win32" and extra == "dgl"
Requires-Dist: dgl==2.2.0; sys_platform == "darwin" and extra == "dgl"
Requires-Dist: dgl<=2.4.0; sys_platform == "linux" and extra == "dgl"
Dynamic: license-file
